timeofsleep.py
timeofsleep-0.0.1.dist-info/METADATA
timeofsleep-0.0.1.dist-info/WHEEL
timeofsleep-0.0.1.dist-info/entry_points.txt
timeofsleep-0.0.1.dist-info/top_level.txt
timeofsleep-0.0.1.dist-info/RECORD
